thunders/__init__.py
thunders/run.py
thunders/task.py
thunders-0.1.6.dist-info/LICENSE
thunders-0.1.6.dist-info/METADATA
thunders-0.1.6.dist-info/WHEEL
thunders-0.1.6.dist-info/entry_points.txt
thunders-0.1.6.dist-info/top_level.txt
thunders-0.1.6.dist-info/RECORD
