Metadata-Version: 2.1
Name: thunders
Version: 0.1.6
Summary: 迅雷非官方批量下载SDK
Home-page: https://leesoar.com/explore
Author: leesoar
Author-email: core@111.com
License: MIT
Keywords: thunder,downloader,thunders
Platform: UNKNOWN
Classifier: License :: OSI Approved :: MIT License
Classifier: Programming Language :: Python :: 3.5
Classifier: Programming Language :: Python :: 3.6
Classifier: Programming Language :: Python :: 3.7
Classifier: Programming Language :: Python :: Implementation :: CPython
Classifier: Programming Language :: Python :: Implementation :: PyPy
Requires-Python: >=3.3.0
Requires-Dist: pyperclip
